[{"StoreNumber":"0079","BrandName":"Stanton Optical","StoreName":"Stanton Optical - National City","Language":"English","Address":"1000 Highland Ave","StateName":"California","CITY":"National City","ZipCode":"91950","TimeZon":"PST","StoreLabStatus":"None","StoreDetails":"-","StoreScriptOperning":"-","LandMarks":"We're located in the intersection of E Plaza Blvd and Highland Ave, caddy-corner of Firestone Complete Auto Care and across the street from Wingstop.","Alerts":null,"Latitude":32.6761572,"Longitude":-117.0981947,"Schedules":[{"Name":"Monday","WorkingHourStartTime":"10:00:00","WorkingHourEndTime":"18:00:00","TimeZone":"PACIFIC STANDARD TIME","TimeOffSet":"1900-01-01T02:00:00-08:00","WorkingHourStartTimeEST":"05:00:00","WorkingHourEndTimeEST":"13:00:00","StoreNumber":"0079"},{"Name":"Tuesday","WorkingHourStartTime":"10:00:00","WorkingHourEndTime":"18:00:00","TimeZone":"PACIFIC STANDARD TIME","TimeOffSet":"1900-01-01T02:00:00-08:00","WorkingHourStartTimeEST":"05:00:00","WorkingHourEndTimeEST":"13:00:00","StoreNumber":"0079"},{"Name":"Wednesday","WorkingHourStartTime":"10:00:00","WorkingHourEndTime":"18:00:00","TimeZone":"PACIFIC STANDARD TIME","TimeOffSet":"1900-01-01T02:00:00-08:00","WorkingHourStartTimeEST":"05:00:00","WorkingHourEndTimeEST":"13:00:00","StoreNumber":"0079"},{"Name":"Thursday","WorkingHourStartTime":"10:00:00","WorkingHourEndTime":"18:00:00","TimeZone":"PACIFIC STANDARD TIME","TimeOffSet":"1900-01-01T02:00:00-08:00","WorkingHourStartTimeEST":"05:00:00","WorkingHourEndTimeEST":"13:00:00","StoreNumber":"0079"},{"Name":"Friday","WorkingHourStartTime":"10:00:00","WorkingHourEndTime":"18:00:00","TimeZone":"PACIFIC STANDARD TIME","TimeOffSet":"1900-01-01T02:00:00-08:00","WorkingHourStartTimeEST":"05:00:00","WorkingHourEndTimeEST":"13:00:00","StoreNumber":"0079"},{"Name":"Saturday","WorkingHourStartTime":"10:00:00","WorkingHourEndTime":"18:00:00","TimeZone":"PACIFIC STANDARD TIME","TimeOffSet":"1900-01-01T02:00:00-08:00","WorkingHourStartTimeEST":"05:00:00","WorkingHourEndTimeEST":"13:00:00","StoreNumber":"0079"},{"Name":"Sunday","WorkingHourStartTime":"00:00:00","WorkingHourEndTime":"00:00:00","TimeZone":null,"TimeOffSet":null,"WorkingHourStartTimeEST":null,"WorkingHourEndTimeEST":null,"StoreNumber":"0079"}],"Phones":[{"StoreNumber":"0079","PhoneNumber":"6195059158","Name":"Main"},{"StoreNumber":"0079","PhoneNumber":"6192452103","Name":"Fax"},{"StoreNumber":"0079","PhoneNumber":"6193634430","Name":"Google"}]}]